[
    {
        "area": "Mondragone-Capua",
        "current_generation": 24,
        "total_generations": 50,
        "resolution": 200,
        "population": 3500,
        "scenarios": 0,
        "best_individual": "mul(add(distance, if_then_else(is_water, 0.09, if_then_else(is_water, 0.343, steepness))), 0.01)",
        "best_individual_fitness": [
            97.73775153818191
        ],
        "hall_of_fame": [
            {
                "individual": "mul(add(distance, if_then_else(is_water, 0.09, if_then_else(is_water, 0.343, steepness))), 0.01)",
                "fitness": 97.73775153818191
            },
            {
                "individual": "mul(0.009, add(distance, if_then_else(is_water, if_then_else(is_water, 0.629, steepness), steepness)))",
                "fitness": 97.73775153818191
            },
            {
                "individual": "mul(add(distance, if_then_else(is_water, 0.09, steepness)), 0.01)",
                "fitness": 97.73775153818191
            },
            {
                "individual": "mul(add(distance, if_then_else(is_water, if_then_else(is_water, 0.145, 0.025), steepness)), 0.009)",
                "fitness": 97.73775153818191
            },
            {
                "individual": "mul(neg(neg(0.005)), add(distance, if_then_else(is_water, 0.239, steepness)))",
                "fitness": 97.73775153818191
            }
        ],
        "runtime_in_seconds": 20.020830392837524
    }
]