[
    {
        "area": "Trentino",
        "current_generation": 3,
        "total_generations": 50,
        "resolution": 200,
        "population": 3500,
        "scenarios": 0,
        "best_individual": "neg(protected_pow(if_then_else(is_water, steepness, 0.654), add(steepness, distance)))",
        "best_individual_fitness": [
            97.74280902084051
        ],
        "hall_of_fame": [
            {
                "individual": "neg(protected_pow(if_then_else(is_water, steepness, 0.654), add(steepness, distance)))",
                "fitness": 97.74280902084051
            },
            {
                "individual": "add(if_then_else(is_water, if_then_else(is_water, distance, 0.904), steepness), add(distance, add(step_penalty_multiplier(steepness, distance, 0.932), if_then_else(is_water, distance, 0.755))))",
                "fitness": 97.745690035461
            },
            {
                "individual": "add(if_then_else(is_water, if_then_else(is_water, 0.612, distance), steepness), add(0.78, distance))",
                "fitness": 97.74993328836294
            },
            {
                "individual": "add(if_then_else(is_water, distance, steepness), add(distance, step_penalty_multiplier(0.508, distance, steepness)))",
                "fitness": 97.75159305798144
            },
            {
                "individual": "add(if_then_else(is_water, 0.948, steepness), add(0.78, distance))",
                "fitness": 97.75164763287279
            }
        ],
        "runtime_in_seconds": 21.002366542816162
    }
]